Workbook

Sheet Portfolio & Rebalancing
A1: 🦅 DYNASTIE-DEPOT – Rebalancing Tool v3.3
A2: 46127
A4: Position | B4: Ticker | C4: Typ | D4: Broker | E4: US- Faktor | F4: Depotwert € | G4: Ist- Anteil % | H4: Ziel- Anteil % | I4: Zielwert € | J4: Fehlbetrag € | K4: Abw. % | L4: Aktion | M4: ⚠️ Cap- Check | N4: DEFCON Score | O4: 🚩 FLAG-Status | P4: 💶 Sparrate €/Monat
A5: EUWAX Gold | B5: EWG2 | C5: Gold | D5: Scalable | E5: 0 | F5: 507 | G5: =IF(F$25=0,0,F5/F$25) -> 0.044615475 | H5: 0.05 | I5: =H5*F$25 -> 568.1885 | J5: =I5-F5 -> 61.1885 | K5: =G5-H5 -> -0.0053845247 | L5: =IF(C5="Aktie",IF(K5>'Parameter & Regeln'!B$9,"📉 Reduzieren",IF(K5<-'Parameter & Regeln'!B$9,"📈 Aufstocken","⚖️ Halten")),IF(C5="Gold",IF(K5>'Parameter & Regeln'!B$8,"📉 Reduzieren",IF(K5<-'Parameter & Regeln'!B$8,"📈 Aufstocken","⚖️ Halten")),IF(K5>'Parameter & Regeln'!B$8,"📉 Reduzieren",IF(K5<-'Parameter & Regeln'!B$8,"📈 Aufstocken","⚖️ Halten")))) -> ⚖️ Halten | M5: =IF(C5="Aktie",IF(G5>'Parameter & Regeln'!B$10,"🚨 ÜBER CAP","✅ OK"),"") | P5: =IF(OR(C5="ETF",C5="Gold"),(H5/SUMIF($C$5:$C$20,"<>Aktie",$H$5:$H$20))*('Parameter & Regeln'!$B$4*('Parameter & Regeln'!$B$5+'Parameter & Regeln'!$B$7)),"") -> 47.5
A6: iShares MSCI World | B6: IWDA | C6: ETF | D6: ING | E6: 0.7 | F6: 2792.3 | G6: =IF(F$25=0,0,F6/F$25) -> 0.24571951 | H6: 0.3 | I6: =H6*F$25 -> 3409.131 | J6: =I6-F6 -> 616.831 | K6: =G6-H6 -> -0.05428049 | L6: =IF(C6="Aktie",IF(K6>'Parameter & Regeln'!B$9,"📉 Reduzieren",IF(K6<-'Parameter & Regeln'!B$9,"📈 Aufstocken","⚖️ Halten")),IF(C6="Gold",IF(K6>'Parameter & Regeln'!B$8,"📉 Reduzieren",IF(K6<-'Parameter & Regeln'!B$8,"📈 Aufstocken","⚖️ Halten")),IF(K6>'Parameter & Regeln'!B$8,"📉 Reduzieren",IF(K6<-'Parameter & Regeln'!B$8,"📈 Aufstocken","⚖️ Halten")))) -> 📈 Aufstocken | M6: =IF(C6="Aktie",IF(G6>'Parameter & Regeln'!B$10,"🚨 ÜBER CAP","✅ OK"),"") | P6: =IF(OR(C6="ETF",C6="Gold"),(H6/SUMIF($C$5:$C$20,"<>Aktie",$H$5:$H$20))*('Parameter & Regeln'!$B$4*('Parameter & Regeln'!$B$5+'Parameter & Regeln'!$B$7)),"") -> 285
A7: iShares MSCI EM IMI | B7: EIMI | C7: ETF | D7: ING | E7: 0 | F7: 913.01 | G7: =IF(F$25=0,0,F7/F$25) -> 0.080343935 | H7: 0.1 | I7: =H7*F$25 -> 1136.377 | J7: =I7-F7 -> 223.367 | K7: =G7-H7 -> -0.019656065 | L7: =IF(C7="Aktie",IF(K7>'Parameter & Regeln'!B$9,"📉 Reduzieren",IF(K7<-'Parameter & Regeln'!B$9,"📈 Aufstocken","⚖️ Halten")),IF(C7="Gold",IF(K7>'Parameter & Regeln'!B$8,"📉 Reduzieren",IF(K7<-'Parameter & Regeln'!B$8,"📈 Aufstocken","⚖️ Halten")),IF(K7>'Parameter & Regeln'!B$8,"📉 Reduzieren",IF(K7<-'Parameter & Regeln'!B$8,"📈 Aufstocken","⚖️ Halten")))) -> 📈 Aufstocken | M7: =IF(C7="Aktie",IF(G7>'Parameter & Regeln'!B$10,"🚨 ÜBER CAP","✅ OK"),"") | P7: =IF(OR(C7="ETF",C7="Gold"),(H7/SUMIF($C$5:$C$20,"<>Aktie",$H$5:$H$20))*('Parameter & Regeln'!$B$4*('Parameter & Regeln'!$B$5+'Parameter & Regeln'!$B$7)),"") -> 95
A8: MSCI World ex-USA | B8: EXUSA | C8: ETF | D8: ING | E8: 0 | F8: 917.46 | G8: =IF(F$25=0,0,F8/F$25) -> 0.080735531 | H8: 0.15 | I8: =H8*F$25 -> 1704.5655 | J8: =I8-F8 -> 787.1055 | K8: =G8-H8 -> -0.069264469 | L8: =IF(C8="Aktie",IF(K8>'Parameter & Regeln'!B$9,"📉 Reduzieren",IF(K8<-'Parameter & Regeln'!B$9,"📈 Aufstocken","⚖️ Halten")),IF(C8="Gold",IF(K8>'Parameter & Regeln'!B$8,"📉 Reduzieren",IF(K8<-'Parameter & Regeln'!B$8,"📈 Aufstocken","⚖️ Halten")),IF(K8>'Parameter & Regeln'!B$8,"📉 Reduzieren",IF(K8<-'Parameter & Regeln'!B$8,"📈 Aufstocken","⚖️ Halten")))) -> 📈 Aufstocken | M8: =IF(C8="Aktie",IF(G8>'Parameter & Regeln'!B$10,"🚨 ÜBER CAP","✅ OK"),"") | P8: =IF(OR(C8="ETF",C8="Gold"),(H8/SUMIF($C$5:$C$20,"<>Aktie",$H$5:$H$20))*('Parameter & Regeln'!$B$4*('Parameter & Regeln'!$B$5+'Parameter & Regeln'!$B$7)),"") -> 142.5
A9: Avantis Small Cap Value | B9: AVGC | C9: ETF | D9: Scalable | E9: 0.67 | F9: 1001 | G9: =IF(F$25=0,0,F9/F$25) -> 0.088086964 | H9: 0.1 | I9: =H9*F$25 -> 1136.377 | J9: =I9-F9 -> 135.377 | K9: =G9-H9 -> -0.011913036 | L9: =IF(C9="Aktie",IF(K9>'Parameter & Regeln'!B$9,"📉 Reduzieren",IF(K9<-'Parameter & Regeln'!B$9,"📈 Aufstocken","⚖️ Halten")),IF(C9="Gold",IF(K9>'Parameter & Regeln'!B$8,"📉 Reduzieren",IF(K9<-'Parameter & Regeln'!B$8,"📈 Aufstocken","⚖️ Halten")),IF(K9>'Parameter & Regeln'!B$8,"📉 Reduzieren",IF(K9<-'Parameter & Regeln'!B$8,"📈 Aufstocken","⚖️ Halten")))) -> ⚖️ Halten | M9: =IF(C9="Aktie",IF(G9>'Parameter & Regeln'!B$10,"🚨 ÜBER CAP","✅ OK"),"") | P9: =IF(OR(C9="ETF",C9="Gold"),(H9/SUMIF($C$5:$C$20,"<>Aktie",$H$5:$H$20))*('Parameter & Regeln'!$B$4*('Parameter & Regeln'!$B$5+'Parameter & Regeln'!$B$7)),"") -> 95
A10: ASML Holding | B10: ASML | C10: Aktie | D10: Scalable | E10: 0 | F10: 364 | G10: =IF(F$25=0,0,F10/F$25) -> 0.032031623 | H10: 0.0273 | I10: =H10*F$25 -> 310.23092 | J10: =I10-F10 -> -53.769079 | K10: =G10-H10 -> 0.0047316233 | L10: =IF(C10="Aktie",IF(K10>'Parameter & Regeln'!B$9,"📉 Reduzieren",IF(K10<-'Parameter & Regeln'!B$9,"📈 Aufstocken","⚖️ Halten")),IF(C10="Gold",IF(K10>'Parameter & Regeln'!B$8,"📉 Reduzieren",IF(K10<-'Parameter & Regeln'!B$8,"📈 Aufstocken","⚖️ Halten")),IF(K10>'Parameter & Regeln'!B$8,"📉 Reduzieren",IF(K10<-'Parameter & Regeln'!B$8,"📈 Aufstocken","⚖️ Halten")))) -> ⚖️ Halten | M10: =IF(C10="Aktie",IF(G10>'Parameter & Regeln'!B$10,"🚨 ÜBER CAP","✅ OK"),"") -> ✅ OK | N10: DEFCON 3 (68) | O10: 🟡 DEFCON 3 (68) | China Rev 14.7% Risk-Map | 50% Sockelbetrag | P10: =IF(C10<>"Aktie","",IF(LEFT(O10,1)="🔴",0,IF(LEFT(N10,8)="DEFCON 4",IF(O10="✅ Clean",('Parameter & Regeln'!$B$4*'Parameter & Regeln'!$B$6/(COUNTIFS($C$5:$C$20,"Aktie",$N$5:$N$20,"DEFCON 4*",$O$5:$O$20,"✅ Clean")+(COUNTIFS($C$5:$C$20,"Aktie",$N$5:$N$20,"DEFCON 3*")*'Parameter & Regeln'!$B$27))),""),IF(LEFT(N10,8)="DEFCON 3",('Parameter & Regeln'!$B$4*'Parameter & Regeln'!$B$6*'Parameter & Regeln'!$B$27/(COUNTIFS($C$5:$C$20,"Aktie",$N$5:$N$20,"DEFCON 4*",$O$5:$O$20,"✅ Clean")+(COUNTIFS($C$5:$C$20,"Aktie",$N$5:$N$20,"DEFCON 3*")*'Parameter & Regeln'!$B$27))),"")))) -> 19
A11: Broadcom | B11: AVGO | C11: Aktie | D11: Scalable | E11: 1 | F11: 356 | G11: =IF(F$25=0,0,F11/F$25) -> 0.031327632 | H11: 0.0273 | I11: =H11*F$25 -> 310.23092 | J11: =I11-F11 -> -45.769079 | K11: =G11-H11 -> 0.0040276316 | L11: =IF(C11="Aktie",IF(K11>'Parameter & Regeln'!B$9,"📉 Reduzieren",IF(K11<-'Parameter & Regeln'!B$9,"📈 Aufstocken","⚖️ Halten")),IF(C11="Gold",IF(K11>'Parameter & Regeln'!B$8,"📉 Reduzieren",IF(K11<-'Parameter & Regeln'!B$8,"📈 Aufstocken","⚖️ Halten")),IF(K11>'Parameter & Regeln'!B$8,"📉 Reduzieren",IF(K11<-'Parameter & Regeln'!B$8,"📈 Aufstocken","⚖️ Halten")))) -> ⚖️ Halten | M11: =IF(C11="Aktie",IF(G11>'Parameter & Regeln'!B$10,"🚨 ÜBER CAP","✅ OK"),"") -> ✅ OK | N11: DEFCON 4 (86) | O11: ✅ Clean (Insider-Check ausstehend — OpenInsider vor Q3 FY26 Earnings prüfen) | P11: =IF(C11<>"Aktie","",IF(LEFT(O11,1)="🔴",0,IF(LEFT(N11,8)="DEFCON 4",IF(O11="✅ Clean",('Parameter & Regeln'!$B$4*'Parameter & Regeln'!$B$6/(COUNTIFS($C$5:$C$20,"Aktie",$N$5:$N$20,"DEFCON 4*",$O$5:$O$20,"✅ Clean")+(COUNTIFS($C$5:$C$20,"Aktie",$N$5:$N$20,"DEFCON 3*")*'Parameter & Regeln'!$B$27))),""),IF(LEFT(N11,8)="DEFCON 3",('Parameter & Regeln'!$B$4*'Parameter & Regeln'!$B$6*'Parameter & Regeln'!$B$27/(COUNTIFS($C$5:$C$20,"Aktie",$N$5:$N$20,"DEFCON 4*",$O$5:$O$20,"✅ Clean")+(COUNTIFS($C$5:$C$20,"Aktie",$N$5:$N$20,"DEFCON 3*")*'Parameter & Regeln'!$B$27))),""))))
A12: Microsoft | B12: MSFT | C12: Aktie | D12: Scalable | E12: 1 | F12: 301 | G12: =IF(F$25=0,0,F12/F$25) -> 0.026487689 | H12: 0.0273 | I12: =H12*F$25 -> 310.23092 | J12: =I12-F12 -> 9.230921 | K12: =G12-H12 -> -0.0008123115 | L12: =IF(C12="Aktie",IF(K12>'Parameter & Regeln'!B$9,"📉 Reduzieren",IF(K12<-'Parameter & Regeln'!B$9,"📈 Aufstocken","⚖️ Halten")),IF(C12="Gold",IF(K12>'Parameter & Regeln'!B$8,"📉 Reduzieren",IF(K12<-'Parameter & Regeln'!B$8,"📈 Aufstocken","⚖️ Halten")),IF(K12>'Parameter & Regeln'!B$8,"📉 Reduzieren",IF(K12<-'Parameter & Regeln'!B$8,"📈 Aufstocken","⚖️ Halten")))) -> ⚖️ Halten | M12: =IF(C12="Aktie",IF(G12>'Parameter & Regeln'!B$10,"🚨 ÜBER CAP","✅ OK"),"") -> ✅ OK | N12: DEFCON 2 (60) | O12: 🔴 FLAG: CapEx/OCF >60% | Score 60 | DEFCON 2 | Re-Check 29.04. | P12: =IF(C12<>"Aktie","",IF(LEFT(O12,1)="🔴",0,IF(LEFT(N12,8)="DEFCON 4",IF(O12="✅ Clean",('Parameter & Regeln'!$B$4*'Parameter & Regeln'!$B$6/(COUNTIFS($C$5:$C$20,"Aktie",$N$5:$N$20,"DEFCON 4*",$O$5:$O$20,"✅ Clean")+(COUNTIFS($C$5:$C$20,"Aktie",$N$5:$N$20,"DEFCON 3*")*'Parameter & Regeln'!$B$27))),""),IF(LEFT(N12,8)="DEFCON 3",('Parameter & Regeln'!$B$4*'Parameter & Regeln'!$B$6*'Parameter & Regeln'!$B$27/(COUNTIFS($C$5:$C$20,"Aktie",$N$5:$N$20,"DEFCON 4*",$O$5:$O$20,"✅ Clean")+(COUNTIFS($C$5:$C$20,"Aktie",$N$5:$N$20,"DEFCON 3*")*'Parameter & Regeln'!$B$27))),"")))) -> 0
A13: Costco | B13: COST | C13: Aktie | D13: Scalable | E13: 1 | F13: 350 | G13: =IF(F$25=0,0,F13/F$25) -> 0.030799638 | H13: 0.0273 | I13: =H13*F$25 -> 310.23092 | J13: =I13-F13 -> -39.769079 | K13: =G13-H13 -> 0.0034996378 | L13: =IF(C13="Aktie",IF(K13>'Parameter & Regeln'!B$9,"📉 Reduzieren",IF(K13<-'Parameter & Regeln'!B$9,"📈 Aufstocken","⚖️ Halten")),IF(C13="Gold",IF(K13>'Parameter & Regeln'!B$8,"📉 Reduzieren",IF(K13<-'Parameter & Regeln'!B$8,"📈 Aufstocken","⚖️ Halten")),IF(K13>'Parameter & Regeln'!B$8,"📉 Reduzieren",IF(K13<-'Parameter & Regeln'!B$8,"📈 Aufstocken","⚖️ Halten")))) -> ⚖️ Halten | M13: =IF(C13="Aktie",IF(G13>'Parameter & Regeln'!B$10,"🚨 ÜBER CAP","✅ OK"),"") -> ✅ OK | N13: DEFCON 4 (~80) | O13: ✅ Clean | P13: =IF(C13<>"Aktie","",IF(LEFT(O13,1)="🔴",0,IF(LEFT(N13,8)="DEFCON 4",IF(O13="✅ Clean",('Parameter & Regeln'!$B$4*'Parameter & Regeln'!$B$6/(COUNTIFS($C$5:$C$20,"Aktie",$N$5:$N$20,"DEFCON 4*",$O$5:$O$20,"✅ Clean")+(COUNTIFS($C$5:$C$20,"Aktie",$N$5:$N$20,"DEFCON 3*")*'Parameter & Regeln'!$B$27))),""),IF(LEFT(N13,8)="DEFCON 3",('Parameter & Regeln'!$B$4*'Parameter & Regeln'!$B$6*'Parameter & Regeln'!$B$27/(COUNTIFS($C$5:$C$20,"Aktie",$N$5:$N$20,"DEFCON 4*",$O$5:$O$20,"✅ Clean")+(COUNTIFS($C$5:$C$20,"Aktie",$N$5:$N$20,"DEFCON 3*")*'Parameter & Regeln'!$B$27))),"")))) -> 38
A14: Hermès | B14: RMS | C14: Aktie | D14: Scalable | E14: 0 | F14: 377 | G14: =IF(F$25=0,0,F14/F$25) -> 0.03317561 | H14: 0.0273 | I14: =H14*F$25 -> 310.23092 | J14: =I14-F14 -> -66.769079 | K14: =G14-H14 -> 0.0058756099 | L14: =IF(C14="Aktie",IF(K14>'Parameter & Regeln'!B$9,"📉 Reduzieren",IF(K14<-'Parameter & Regeln'!B$9,"📈 Aufstocken","⚖️ Halten")),IF(C14="Gold",IF(K14>'Parameter & Regeln'!B$8,"📉 Reduzieren",IF(K14<-'Parameter & Regeln'!B$8,"📈 Aufstocken","⚖️ Halten")),IF(K14>'Parameter & Regeln'!B$8,"📉 Reduzieren",IF(K14<-'Parameter & Regeln'!B$8,"📈 Aufstocken","⚖️ Halten")))) -> ⚖️ Halten | M14: =IF(C14="Aktie",IF(G14>'Parameter & Regeln'!B$10,"🚨 ÜBER CAP","✅ OK"),"") -> ✅ OK | N14: DEFCON 4 (71) | O14: ✅ Clean | P14: =IF(C14<>"Aktie","",IF(LEFT(O14,1)="🔴",0,IF(LEFT(N14,8)="DEFCON 4",IF(O14="✅ Clean",('Parameter & Regeln'!$B$4*'Parameter & Regeln'!$B$6/(COUNTIFS($C$5:$C$20,"Aktie",$N$5:$N$20,"DEFCON 4*",$O$5:$O$20,"✅ Clean")+(COUNTIFS($C$5:$C$20,"Aktie",$N$5:$N$20,"DEFCON 3*")*'Parameter & Regeln'!$B$27))),""),IF(LEFT(N14,8)="DEFCON 3",('Parameter & Regeln'!$B$4*'Parameter & Regeln'!$B$6*'Parameter & Regeln'!$B$27/(COUNTIFS($C$5:$C$20,"Aktie",$N$5:$N$20,"DEFCON 4*",$O$5:$O$20,"✅ Clean")+(COUNTIFS($C$5:$C$20,"Aktie",$N$5:$N$20,"DEFCON 3*")*'Parameter & Regeln'!$B$27))),"")))) -> 38
A15: Veeva Systems | B15: VEEV | C15: Aktie | D15: Scalable | E15: 1 | F15: 323 | G15: =IF(F$25=0,0,F15/F$25) -> 0.028423666 | H15: 0.0273 | I15: =H15*F$25 -> 310.23092 | J15: =I15-F15 -> -12.769079 | K15: =G15-H15 -> 0.0011236657 | L15: =IF(C15="Aktie",IF(K15>'Parameter & Regeln'!B$9,"📉 Reduzieren",IF(K15<-'Parameter & Regeln'!B$9,"📈 Aufstocken","⚖️ Halten")),IF(C15="Gold",IF(K15>'Parameter & Regeln'!B$8,"📉 Reduzieren",IF(K15<-'Parameter & Regeln'!B$8,"📈 Aufstocken","⚖️ Halten")),IF(K15>'Parameter & Regeln'!B$8,"📉 Reduzieren",IF(K15<-'Parameter & Regeln'!B$8,"📈 Aufstocken","⚖️ Halten")))) -> ⚖️ Halten | M15: =IF(C15="Aktie",IF(G15>'Parameter & Regeln'!B$10,"🚨 ÜBER CAP","✅ OK"),"") -> ✅ OK | N15: DEFCON 4 (74) | O15: ✅ Clean | P15: =IF(C15<>"Aktie","",IF(LEFT(O15,1)="🔴",0,IF(LEFT(N15,8)="DEFCON 4",IF(O15="✅ Clean",('Parameter & Regeln'!$B$4*'Parameter & Regeln'!$B$6/(COUNTIFS($C$5:$C$20,"Aktie",$N$5:$N$20,"DEFCON 4*",$O$5:$O$20,"✅ Clean")+(COUNTIFS($C$5:$C$20,"Aktie",$N$5:$N$20,"DEFCON 3*")*'Parameter & Regeln'!$B$27))),""),IF(LEFT(N15,8)="DEFCON 3",('Parameter & Regeln'!$B$4*'Parameter & Regeln'!$B$6*'Parameter & Regeln'!$B$27/(COUNTIFS($C$5:$C$20,"Aktie",$N$5:$N$20,"DEFCON 4*",$O$5:$O$20,"✅ Clean")+(COUNTIFS($C$5:$C$20,"Aktie",$N$5:$N$20,"DEFCON 3*")*'Parameter & Regeln'!$B$27))),"")))) -> 38
A16: Schneider Electric | B16: SU | C16: Aktie | D16: Scalable | E16: 0 | F16: 336 | G16: =IF(F$25=0,0,F16/F$25) -> 0.029567652 | H16: 0.0273 | I16: =H16*F$25 -> 310.23092 | J16: =I16-F16 -> -25.769079 | K16: =G16-H16 -> 0.0022676523 | L16: =IF(C16="Aktie",IF(K16>'Parameter & Regeln'!B$9,"📉 Reduzieren",IF(K16<-'Parameter & Regeln'!B$9,"📈 Aufstocken","⚖️ Halten")),IF(C16="Gold",IF(K16>'Parameter & Regeln'!B$8,"📉 Reduzieren",IF(K16<-'Parameter & Regeln'!B$8,"📈 Aufstocken","⚖️ Halten")),IF(K16>'Parameter & Regeln'!B$8,"📉 Reduzieren",IF(K16<-'Parameter & Regeln'!B$8,"📈 Aufstocken","⚖️ Halten")))) -> ⚖️ Halten | M16: =IF(C16="Aktie",IF(G16>'Parameter & Regeln'!B$10,"🚨 ÜBER CAP","✅ OK"),"") -> ✅ OK | N16: DEFCON 4 (~80) | O16: ✅ Clean | P16: =IF(C16<>"Aktie","",IF(LEFT(O16,1)="🔴",0,IF(LEFT(N16,8)="DEFCON 4",IF(O16="✅ Clean",('Parameter & Regeln'!$B$4*'Parameter & Regeln'!$B$6/(COUNTIFS($C$5:$C$20,"Aktie",$N$5:$N$20,"DEFCON 4*",$O$5:$O$20,"✅ Clean")+(COUNTIFS($C$5:$C$20,"Aktie",$N$5:$N$20,"DEFCON 3*")*'Parameter & Regeln'!$B$27))),""),IF(LEFT(N16,8)="DEFCON 3",('Parameter & Regeln'!$B$4*'Parameter & Regeln'!$B$6*'Parameter & Regeln'!$B$27/(COUNTIFS($C$5:$C$20,"Aktie",$N$5:$N$20,"DEFCON 4*",$O$5:$O$20,"✅ Clean")+(COUNTIFS($C$5:$C$20,"Aktie",$N$5:$N$20,"DEFCON 3*")*'Parameter & Regeln'!$B$27))),"")))) -> 38
A17: Berkshire Hathaway | B17: BRK.B | C17: Aktie | D17: Scalable | E17: 1 | F17: 403 | G17: =IF(F$25=0,0,F17/F$25) -> 0.035463583 | H17: 0.0273 | I17: =H17*F$25 -> 310.23092 | J17: =I17-F17 -> -92.769079 | K17: =G17-H17 -> 0.0081635829 | L17: =IF(C17="Aktie",IF(K17>'Parameter & Regeln'!B$9,"📉 Reduzieren",IF(K17<-'Parameter & Regeln'!B$9,"📈 Aufstocken","⚖️ Halten")),IF(C17="Gold",IF(K17>'Parameter & Regeln'!B$8,"📉 Reduzieren",IF(K17<-'Parameter & Regeln'!B$8,"📈 Aufstocken","⚖️ Halten")),IF(K17>'Parameter & Regeln'!B$8,"📉 Reduzieren",IF(K17<-'Parameter & Regeln'!B$8,"📈 Aufstocken","⚖️ Halten")))) -> ⚖️ Halten | M17: =IF(C17="Aktie",IF(G17>'Parameter & Regeln'!B$10,"🚨 ÜBER CAP","✅ OK"),"") -> ✅ OK | N17: DEFCON 4 (~80) | O17: ✅ Clean | P17: =IF(C17<>"Aktie","",IF(LEFT(O17,1)="🔴",0,IF(LEFT(N17,8)="DEFCON 4",IF(O17="✅ Clean",('Parameter & Regeln'!$B$4*'Parameter & Regeln'!$B$6/(COUNTIFS($C$5:$C$20,"Aktie",$N$5:$N$20,"DEFCON 4*",$O$5:$O$20,"✅ Clean")+(COUNTIFS($C$5:$C$20,"Aktie",$N$5:$N$20,"DEFCON 3*")*'Parameter & Regeln'!$B$27))),""),IF(LEFT(N17,8)="DEFCON 3",('Parameter & Regeln'!$B$4*'Parameter & Regeln'!$B$6*'Parameter & Regeln'!$B$27/(COUNTIFS($C$5:$C$20,"Aktie",$N$5:$N$20,"DEFCON 4*",$O$5:$O$20,"✅ Clean")+(COUNTIFS($C$5:$C$20,"Aktie",$N$5:$N$20,"DEFCON 3*")*'Parameter & Regeln'!$B$27))),"")))) -> 38
A18: Visa | B18: V | C18: Aktie | D18: Scalable | E18: 1 | F18: 416 | G18: =IF(F$25=0,0,F18/F$25) -> 0.036607569 | H18: 0.0273 | I18: =H18*F$25 -> 310.23092 | J18: =I18-F18 -> -105.76908 | K18: =G18-H18 -> 0.0093075695 | L18: =IF(C18="Aktie",IF(K18>'Parameter & Regeln'!B$9,"📉 Reduzieren",IF(K18<-'Parameter & Regeln'!B$9,"📈 Aufstocken","⚖️ Halten")),IF(C18="Gold",IF(K18>'Parameter & Regeln'!B$8,"📉 Reduzieren",IF(K18<-'Parameter & Regeln'!B$8,"📈 Aufstocken","⚖️ Halten")),IF(K18>'Parameter & Regeln'!B$8,"📉 Reduzieren",IF(K18<-'Parameter & Regeln'!B$8,"📈 Aufstocken","⚖️ Halten")))) -> ⚖️ Halten | M18: =IF(C18="Aktie",IF(G18>'Parameter & Regeln'!B$10,"🚨 ÜBER CAP","✅ OK"),"") -> ✅ OK | N18: DEFCON 4 (~80) | O18: ✅ Clean | P18: =IF(C18<>"Aktie","",IF(LEFT(O18,1)="🔴",0,IF(LEFT(N18,8)="DEFCON 4",IF(O18="✅ Clean",('Parameter & Regeln'!$B$4*'Parameter & Regeln'!$B$6/(COUNTIFS($C$5:$C$20,"Aktie",$N$5:$N$20,"DEFCON 4*",$O$5:$O$20,"✅ Clean")+(COUNTIFS($C$5:$C$20,"Aktie",$N$5:$N$20,"DEFCON 3*")*'Parameter & Regeln'!$B$27))),""),IF(LEFT(N18,8)="DEFCON 3",('Parameter & Regeln'!$B$4*'Parameter & Regeln'!$B$6*'Parameter & Regeln'!$B$27/(COUNTIFS($C$5:$C$20,"Aktie",$N$5:$N$20,"DEFCON 4*",$O$5:$O$20,"✅ Clean")+(COUNTIFS($C$5:$C$20,"Aktie",$N$5:$N$20,"DEFCON 3*")*'Parameter & Regeln'!$B$27))),"")))) -> 38
A19: Thermo Fisher | B19: TMO | C19: Aktie | D19: Scalable | E19: 1 | F19: 258 | G19: =IF(F$25=0,0,F19/F$25) -> 0.022703733 | H19: 0.0273 | I19: =H19*F$25 -> 310.23092 | J19: =I19-F19 -> 52.230921 | K19: =G19-H19 -> -0.004596267 | L19: =IF(C19="Aktie",IF(K19>'Parameter & Regeln'!B$9,"📉 Reduzieren",IF(K19<-'Parameter & Regeln'!B$9,"📈 Aufstocken","⚖️ Halten")),IF(C19="Gold",IF(K19>'Parameter & Regeln'!B$8,"📉 Reduzieren",IF(K19<-'Parameter & Regeln'!B$8,"📈 Aufstocken","⚖️ Halten")),IF(K19>'Parameter & Regeln'!B$8,"📉 Reduzieren",IF(K19<-'Parameter & Regeln'!B$8,"📈 Aufstocken","⚖️ Halten")))) -> ⚖️ Halten | M19: =IF(C19="Aktie",IF(G19>'Parameter & Regeln'!B$10,"🚨 ÜBER CAP","✅ OK"),"") -> ✅ OK | N19: DEFCON 3 (67) | O19: 🟡 DEFCON 3 (67) | Clario-Watch | 50% Sockelbetrag | Re-Analyse 23.04. | P19: =IF(C19<>"Aktie","",IF(LEFT(O19,1)="🔴",0,IF(LEFT(N19,8)="DEFCON 4",IF(O19="✅ Clean",('Parameter & Regeln'!$B$4*'Parameter & Regeln'!$B$6/(COUNTIFS($C$5:$C$20,"Aktie",$N$5:$N$20,"DEFCON 4*",$O$5:$O$20,"✅ Clean")+(COUNTIFS($C$5:$C$20,"Aktie",$N$5:$N$20,"DEFCON 3*")*'Parameter & Regeln'!$B$27))),""),IF(LEFT(N19,8)="DEFCON 3",('Parameter & Regeln'!$B$4*'Parameter & Regeln'!$B$6*'Parameter & Regeln'!$B$27/(COUNTIFS($C$5:$C$20,"Aktie",$N$5:$N$20,"DEFCON 4*",$O$5:$O$20,"✅ Clean")+(COUNTIFS($C$5:$C$20,"Aktie",$N$5:$N$20,"DEFCON 3*")*'Parameter & Regeln'!$B$27))),"")))) -> 19
A20: Amphenol | B20: APH | C20: Aktie | D20: Scalable | E20: 1 | F20: 249 | G20: =IF(F$25=0,0,F20/F$25) -> 0.021911742 | H20: 0.0273 | I20: =H20*F$25 -> 310.23092 | J20: =I20-F20 -> 61.230921 | K20: =G20-H20 -> -0.0053882577 | L20: =IF(C20="Aktie",IF(K20>'Parameter & Regeln'!B$9,"📉 Reduzieren",IF(K20<-'Parameter & Regeln'!B$9,"📈 Aufstocken","⚖️ Halten")),IF(C20="Gold",IF(K20>'Parameter & Regeln'!B$8,"📉 Reduzieren",IF(K20<-'Parameter & Regeln'!B$8,"📈 Aufstocken","⚖️ Halten")),IF(K20>'Parameter & Regeln'!B$8,"📉 Reduzieren",IF(K20<-'Parameter & Regeln'!B$8,"📈 Aufstocken","⚖️ Halten")))) -> ⚖️ Halten | M20: =IF(C20="Aktie",IF(G20>'Parameter & Regeln'!B$10,"🚨 ÜBER CAP","✅ OK"),"") -> ✅ OK | N20: DEFCON 3 (61) | O20: 🔴 FLAG: Score 61 (DEFCON 3) | Tariff-Check done: CN 14.7% Risk-Map | Sparrate 0€ | P20: =IF(C20<>"Aktie","",IF(LEFT(O20,1)="🔴",0,IF(LEFT(N20,8)="DEFCON 4",IF(O20="✅ Clean",('Parameter & Regeln'!$B$4*'Parameter & Regeln'!$B$6/(COUNTIFS($C$5:$C$20,"Aktie",$N$5:$N$20,"DEFCON 4*",$O$5:$O$20,"✅ Clean")+(COUNTIFS($C$5:$C$20,"Aktie",$N$5:$N$20,"DEFCON 3*")*'Parameter & Regeln'!$B$27))),""),IF(LEFT(N20,8)="DEFCON 3",('Parameter & Regeln'!$B$4*'Parameter & Regeln'!$B$6*'Parameter & Regeln'!$B$27/(COUNTIFS($C$5:$C$20,"Aktie",$N$5:$N$20,"DEFCON 4*",$O$5:$O$20,"✅ Clean")+(COUNTIFS($C$5:$C$20,"Aktie",$N$5:$N$20,"DEFCON 3*")*'Parameter & Regeln'!$B$27))),"")))) -> 0
A21: 📊 GESAMT | F21: =SUM(F5:F20) -> 9863.77 | G21: =SUM(G5:G20) -> 0.86800155 | H21: =SUM(H5:H20) -> 1.0003 | I21: =SUM(I5:I20) -> 11367.179 | J21: =ROUND(SUM(J5:J20),2) -> 1503.41 | K21: =SUMPRODUCT((C5:C20="Aktie")*ABS(K5:K20))/COUNTIF(C5:C20,"Aktie") -> 0.0045267099 | L21: Ø Drift ges. | M21: =COUNTIF(M5:M20,"🚨 ÜBER CAP") -> 0 | N21: =COUNTIF(N5:N20,"DEFCON 1*")+COUNTIF(N5:N20,"DEFCON 2*")+COUNTIF(N5:N20,"DEFCON 3*") -> 4 | O21: =COUNTIF(O5:O20,"🚩*")+COUNTIF(O5:O20,"🔴*") -> 2 | P21: =SUMIF(C5:C20,"Aktie",P5:P20)+SUMIF(C5:C20,"<>Aktie",P5:P20) -> 931
K22: =SUMPRODUCT((C5:C20<>"Aktie")*ABS(K5:K20))/COUNTIF(C5:C20,"<>Aktie") -> 0.032099717 | L22: Ø ETF/Gold-Drift | M22: =COUNTIF(M5:M9,"🚨 ÜBER CAP") -> 0 | N22: ⚠️ DEFCON ≤ 3 | O22: 🚩 Aktive FLAGs | P22: Check: Sparrate gesamt
A23: Scalable Cash (verfügbar) | F23: 947.77
A24: 📝 Neuinvestition (manuell eingeben) | F24: 1500
A25: Gesamtwert nach Invest | F25: =F21 + F24 -> 11363.77
A26: Noch zu überweisen (ING + Δ Scalable) | F26: =F24 - MIN(F23, SUMIFS(J5:J20, D5:D20, "Scalable", J5:J20, ">0")) -> 1180.7417

Sheet US-Exposure
A1: US-EXPOSURE TRACKER
A3: Position | B3: Ticker | C3: Depotwert € | D3: US-Faktor | E3: US-Anteil €
A4: ='Portfolio & Rebalancing'!A5 -> EUWAX Gold | B4: ='Portfolio & Rebalancing'!B5 -> EWG2 | C4: ='Portfolio & Rebalancing'!F5 -> 507 | D4: ='Portfolio & Rebalancing'!E5 -> 0 | E4: =C4*D4 -> 0
A5: ='Portfolio & Rebalancing'!A6 -> iShares MSCI World | B5: ='Portfolio & Rebalancing'!B6 -> IWDA | C5: ='Portfolio & Rebalancing'!F6 -> 2792.3 | D5: ='Portfolio & Rebalancing'!E6 -> 0.7 | E5: =C5*D5 -> 1954.61
A6: ='Portfolio & Rebalancing'!A7 -> iShares MSCI EM IMI | B6: ='Portfolio & Rebalancing'!B7 -> EIMI | C6: ='Portfolio & Rebalancing'!F7 -> 913.01 | D6: ='Portfolio & Rebalancing'!E7 -> 0 | E6: =C6*D6 -> 0
A7: ='Portfolio & Rebalancing'!A8 -> MSCI World ex-USA | B7: ='Portfolio & Rebalancing'!B8 -> EXUSA | C7: ='Portfolio & Rebalancing'!F8 -> 917.46 | D7: ='Portfolio & Rebalancing'!E8 -> 0 | E7: =C7*D7 -> 0
A8: ='Portfolio & Rebalancing'!A9 -> Avantis Small Cap Value | B8: ='Portfolio & Rebalancing'!B9 -> AVGC | C8: ='Portfolio & Rebalancing'!F9 -> 1001 | D8: ='Portfolio & Rebalancing'!E9 -> 0.67 | E8: =C8*D8 -> 670.67
A9: ='Portfolio & Rebalancing'!A10 -> ASML Holding | B9: ='Portfolio & Rebalancing'!B10 -> ASML | C9: ='Portfolio & Rebalancing'!F10 -> 364 | D9: ='Portfolio & Rebalancing'!E10 -> 0 | E9: =C9*D9 -> 0
A10: ='Portfolio & Rebalancing'!A11 -> Broadcom | B10: ='Portfolio & Rebalancing'!B11 -> AVGO | C10: ='Portfolio & Rebalancing'!F11 -> 356 | D10: ='Portfolio & Rebalancing'!E11 -> 1 | E10: =C10*D10 -> 356
A11: ='Portfolio & Rebalancing'!A12 -> Microsoft | B11: ='Portfolio & Rebalancing'!B12 -> MSFT | C11: ='Portfolio & Rebalancing'!F12 -> 301 | D11: ='Portfolio & Rebalancing'!E12 -> 1 | E11: =C11*D11 -> 301
A12: ='Portfolio & Rebalancing'!A13 -> Costco | B12: ='Portfolio & Rebalancing'!B13 -> COST | C12: ='Portfolio & Rebalancing'!F13 -> 350 | D12: ='Portfolio & Rebalancing'!E13 -> 1 | E12: =C12*D12 -> 350
A13: ='Portfolio & Rebalancing'!A14 -> Hermès | B13: ='Portfolio & Rebalancing'!B14 -> RMS | C13: ='Portfolio & Rebalancing'!F14 -> 377 | D13: ='Portfolio & Rebalancing'!E14 -> 0 | E13: =C13*D13 -> 0
A14: ='Portfolio & Rebalancing'!A15 -> Veeva Systems | B14: ='Portfolio & Rebalancing'!B15 -> VEEV | C14: ='Portfolio & Rebalancing'!F15 -> 323 | D14: ='Portfolio & Rebalancing'!E15 -> 1 | E14: =C14*D14 -> 323
A15: ='Portfolio & Rebalancing'!A16 -> Schneider Electric | B15: ='Portfolio & Rebalancing'!B16 -> SU | C15: ='Portfolio & Rebalancing'!F16 -> 336 | D15: ='Portfolio & Rebalancing'!E16 -> 0 | E15: =C15*D15 -> 0
... A19: ='Portfolio & Rebalancing'!A20 -> Amphenol | B19: ='Portfolio & Rebalancing'!B20 -> APH | C19: ='Portfolio & Rebalancing'!F20 -> 249 | D19: ='Portfolio & Rebalancing'!E20 -> 1 | E19: =C19*D19 -> 249
A20: GESAMT | C20: ='Portfolio & Rebalancing'!F21 -> 9863.77 | E20: =SUM(E4:E19) -> 5281.28
A22: US-Anteil (Ist) | B22: =IF('Portfolio & Rebalancing'!F25=0,0,E20/'Portfolio & Rebalancing'!F25) -> 0.46474717
A23: US-Anteil (Ziel) | B23: =SUMPRODUCT('Portfolio & Rebalancing'!$E$5:$E$20,'Portfolio & Rebalancing'!$I$5:$I$20)/SUM('Portfolio & Rebalancing'!$I$5:$I$20) -> 0.49525142
A24: US-Hard-Cap | B24: ='Parameter & Regeln'!B11 -> 0.63
A25: Status (Ist) | B25: =IF(B22>B24,"⛔ ÜBER CAP","✅ OK") -> ✅ OK
A26: Status (Ziel) | B26: =IF(B23>B24,"⛔ ZIEL ÜBER CAP","✅ Ziel OK") -> ✅ Ziel OK

Sheet Parameter & Regeln
A1: ⚙️ REBALANCING PARAMETER
A3: Parameter | B3: Wert | C3: Einheit
A4: Sparrate monatlich | B4: 950 | C4: €
A5: ETF-Core Zielanteil | B5: 0.65 | C5: %
A6: Satelliten Zielanteil | B6: 0.3 | C6: %
A7: Gold Zielanteil | B7: 0.05 | C7: %
A8: Drift-Toleranz ETF/Gold | B8: 0.015 | C8: %
A9: Drift-Toleranz Aktien | B9: 0.04 | C9: %
A10: Single-Stock-Cap | B10: 0.1 | C10: %
A11: US-Hard-Cap | B11: 0.63 | C11: %
A12: Max Aktien Slots | B12: 11
A13: Aktien-Slots belegt | B13: =COUNTIF('Portfolio & Rebalancing'!C5:C20,"Aktie") -> 11
A14: Gesamt Positionen belegt | B14: =COUNTA('Portfolio & Rebalancing'!A5:A20) -> 16
A15: Drift-Warnschwelle (gelb) | B15: 0.15 | C15: %
A16: Allokations-Check (Summe ETF+Sat+Gold) | B16: =B5+B6+B7 -> 1 | C16: %
A17: 📋 REBALANCING-REGELN
A19: Situation | B19: Bedeutung | C19: Aktion
A20: Abweichung negativ (rot) | B20: Untergewicht | C20: 📈 Sparrate erhöhen/starten
A21: Abweichung positiv (gelb) | B21: Übergewicht | C21: 📉 Sparrate stoppen/drosseln
A22: Innerhalb Toleranz (grün) | B22: Gleichgewicht | C22: ⚖️ Sparrate weiterführen
A23: NIEMALS durch Verkauf rebalancen | B23: Steuer-Bremse | C23: Nur Sparplan umleiten
A25: Satelliten-Budget / Monat | B25: =B4*B6 -> 285 | C25: €
A26: Aktive D4-Clean Positionen (Gewicht 1.0) | B26: =COUNTIFS('Portfolio & Rebalancing'!$C$10:$C$20,"Aktie",'Portfolio & Rebalancing'!$N$10:$N$20,"DEFCON 4*",'Portfolio & Rebalancing'!$O$10:$O$20,"✅ Clean") -> 6
A27: DEFCON-3-Sockelbetrag (% der vollen Rate) | B27: 0.5 | C27: %
A28: 📋 DEFCON-SPARRATEN-LOGIK (v3.3 — 15.04.2026)
A29: DEFCON 4 + ✅ Clean | B29: Volle Sparrate | C29: Budget ÷ (Σ D4-Clean + Σ D3×0.5)
A30: DEFCON 3 (kein FLAG) | B30: 50% Sockelbetrag | C30: Minimales Rebalancing – Position halten
A31: FLAG aktiv (beliebig) oder DEFCON ≤ 2 | B31: 0 € – gestoppt | C31: FLAG überschreibt Score (heilig)
A32: Formel: Budget ÷ (D4-Clean×1.0 + D3×0.5) | B32: =B4*B6/(COUNTIFS('Portfolio & Rebalancing'!$C$10:$C$20,"Aktie",'Portfolio & Rebalancing'!$N$10:$N$20,"DEFCON 4*",'Portfolio & Rebalancing'!$O$10:$O$20,"✅ Clean")+(COUNTIFS('Portfolio & Rebalancing'!$C$10:$C$20,"Aktie",'Portfolio & Rebalancing'!$N$10:$N$20,"DEFCON 3*")*B27)) -> 38 | C32: € = D4-Vollrate
