Workbook

Sheet Portfolio & Rebalancing
A1: 🦅 DYNASTIE-DEPOT – Rebalancing Tool v3.4
A2: 46146
A4: Position | B4: Ticker | C4: Typ | D4: Broker | E4: US- Faktor | F4: Depotwert € | G4: Ist- Anteil % | H4: Ziel- Anteil % | I4: Zielwert € | J4: Fehlbetrag € | K4: Abw. % | L4: Aktion | M4: ⚠️ Cap- Check | N4: DEFCON Score | O4: 🚩 FLAG-Status | P4: 💶 Sparrate €/Monat
A5: EUWAX Gold | B5: EWG2 | C5: Gold | D5: Scalable | E5: 0 | F5: 582 | G5: =IF(F$25=0,0,F5/F$25) -> 0.042218395 | H5: 0.05 | I5: =H5*F$25 -> 689.273 | J5: =I5-F5 -> 107.273 | K5: =G5-H5 -> -0.0077816047 | L5: =IF(C5="Aktie",IF(K5>'Parameter & Regeln'!B$9,"📉 Reduzieren",IF(K5<-'Parameter & Regeln'!B$9,"📈 Aufstocken","⚖️ Halten")),IF(K5>'Parameter & Regeln'!B$8,"📉 Reduzieren",IF(K5<-'Parameter & Regeln'!B$8,"📈 Aufstocken","⚖️ Halten"))) -> ⚖️ Halten | M5: =IF(C5="Aktie",IF(G5>'Parameter & Regeln'!B$10,"🚨 ÜBER CAP","✅ OK"),"") | P5: =IF(OR(C5="ETF",C5="Gold"),(H5/SUMIF($C$5:$C$20,"<>Aktie",$H$5:$H$20))*('Parameter & Regeln'!$B$4*('Parameter & Regeln'!$B$5+'Parameter & Regeln'!$B$7)),IF(C5<>"Aktie","",IF(OR(LEFT(O5,1)="🔴",LEFT(N5,8)="DEFCON 1"),0,IF(LEFT(N5,8)="DEFCON 2",'Parameter & Regeln'!$B$4*'Parameter & Regeln'!$B$6*'Parameter & Regeln'!$B$27/(COUNTIFS($C$5:$C$20,"Aktie",$N$5:$N$20,"DEFCON 4*",$O$5:$O$20,"<>🔴*")+COUNTIFS($C$5:$C$20,"Aktie",$N$5:$N$20,"DEFCON 3*",$O$5:$O$20,"<>🔴*")+COUNTIFS($C$5:$C$20,"Aktie",$N$5:$N$20,"DEFCON 2*",$O$5:$O$20,"<>🔴*")*'Parameter & Regeln'!$B$27),IF(OR(LEFT(N5,8)="DEFCON 4",LEFT(N5,8)="DEFCON 3"),'Parameter & Regeln'!$B$4*'Parameter & Regeln'!$B$6/(COUNTIFS($C$5:$C$20,"Aktie",$N$5:$N$20,"DEFCON 4*",$O$5:$O$20,"<>🔴*")+COUNTIFS($C$5:$C$20,"Aktie",$N$5:$N$20,"DEFCON 3*",$O$5:$O$20,"<>🔴*")+COUNTIFS($C$5:$C$20,"Aktie",$N$5:$N$20,"DEFCON 2*",$O$5:$O$20,"<>🔴*")*'Parameter & Regeln'!$B$27),""))))) -> 47.5
A6: iShares MSCI World | B6: IWDA | C6: ETF | D6: ING | E6: 0.7 | F6: 3675.72 | G6: =IF(F$25=0,0,F6/F$25) -> 0.26663746 | H6: 0.3 | I6: =H6*F$25 -> 4135.638 | J6: =I6-F6 -> 459.918 | K6: =G6-H6 -> -0.033362543 | L6: =IF(C6="Aktie",IF(K6>'Parameter & Regeln'!B$9,"📉 Reduzieren",IF(K6<-'Parameter & Regeln'!B$9,"📈 Aufstocken","⚖️ Halten")),IF(K6>'Parameter & Regeln'!B$8,"📉 Reduzieren",IF(K6<-'Parameter & Regeln'!B$8,"📈 Aufstocken","⚖️ Halten"))) -> 📈 Aufstocken | M6: =IF(C6="Aktie",IF(G6>'Parameter & Regeln'!B$10,"🚨 ÜBER CAP","✅ OK"),"") | P6: =IF(OR(C6="ETF",C6="Gold"),(H6/SUMIF($C$5:$C$20,"<>Aktie",$H$5:$H$20))*('Parameter & Regeln'!$B$4*('Parameter & Regeln'!$B$5+'Parameter & Regeln'!$B$7)),IF(C6<>"Aktie","",IF(OR(LEFT(O6,1)="🔴",LEFT(N6,8)="DEFCON 1"),0,IF(LEFT(N6,8)="DEFCON 2",'Parameter & Regeln'!$B$4*'Parameter & Regeln'!$B$6*'Parameter & Regeln'!$B$27/(COUNTIFS($C$5:$C$20,"Aktie",$N$5:$N$20,"DEFCON 4*",$O$5:$O$20,"<>🔴*")+COUNTIFS($C$5:$C$20,"Aktie",$N$5:$N$20,"DEFCON 3*",$O$5:$O$20,"<>🔴*")+COUNTIFS($C$5:$C$20,"Aktie",$N$5:$N$20,"DEFCON 2*",$O$5:$O$20,"<>🔴*")*'Parameter & Regeln'!$B$27),IF(OR(LEFT(N6,8)="DEFCON 4",LEFT(N6,8)="DEFCON 3"),'Parameter & Regeln'!$B$4*'Parameter & Regeln'!$B$6/(COUNTIFS($C$5:$C$20,"Aktie",$N$5:$N$20,"DEFCON 4*",$O$5:$O$20,"<>🔴*")+COUNTIFS($C$5:$C$20,"Aktie",$N$5:$N$20,"DEFCON 3*",$O$5:$O$20,"<>🔴*")+COUNTIFS($C$5:$C$20,"Aktie",$N$5:$N$20,"DEFCON 2*",$O$5:$O$20,"<>🔴*")*'Parameter & Regeln'!$B$27),""))))) -> 285
A7: iShares MSCI EM IMI | B7: EIMI | C7: ETF | D7: ING | E7: 0 | F7: 1228.3 | G7: =IF(F$25=0,0,F7/F$25) -> 0.089101125 | H7: 0.1 | I7: =H7*F$25 -> 1378.546 | J7: =I7-F7 -> 150.246 | K7: =G7-H7 -> -0.010898875 | L7: =IF(C7="Aktie",IF(K7>'Parameter & Regeln'!B$9,"📉 Reduzieren",IF(K7<-'Parameter & Regeln'!B$9,"📈 Aufstocken","⚖️ Halten")),IF(K7>'Parameter & Regeln'!B$8,"📉 Reduzieren",IF(K7<-'Parameter & Regeln'!B$8,"📈 Aufstocken","⚖️ Halten"))) -> ⚖️ Halten | M7: =IF(C7="Aktie",IF(G7>'Parameter & Regeln'!B$10,"🚨 ÜBER CAP","✅ OK"),"") | P7: =IF(OR(C7="ETF",C7="Gold"),(H7/SUMIF($C$5:$C$20,"<>Aktie",$H$5:$H$20))*('Parameter & Regeln'!$B$4*('Parameter & Regeln'!$B$5+'Parameter & Regeln'!$B$7)),IF(C7<>"Aktie","",IF(OR(LEFT(O7,1)="🔴",LEFT(N7,8)="DEFCON 1"),0,IF(LEFT(N7,8)="DEFCON 2",'Parameter & Regeln'!$B$4*'Parameter & Regeln'!$B$6*'Parameter & Regeln'!$B$27/(COUNTIFS($C$5:$C$20,"Aktie",$N$5:$N$20,"DEFCON 4*",$O$5:$O$20,"<>🔴*")+COUNTIFS($C$5:$C$20,"Aktie",$N$5:$N$20,"DEFCON 3*",$O$5:$O$20,"<>🔴*")+COUNTIFS($C$5:$C$20,"Aktie",$N$5:$N$20,"DEFCON 2*",$O$5:$O$20,"<>🔴*")*'Parameter & Regeln'!$B$27),IF(OR(LEFT(N7,8)="DEFCON 4",LEFT(N7,8)="DEFCON 3"),'Parameter & Regeln'!$B$4*'Parameter & Regeln'!$B$6/(COUNTIFS($C$5:$C$20,"Aktie",$N$5:$N$20,"DEFCON 4*",$O$5:$O$20,"<>🔴*")+COUNTIFS($C$5:$C$20,"Aktie",$N$5:$N$20,"DEFCON 3*",$O$5:$O$20,"<>🔴*")+COUNTIFS($C$5:$C$20,"Aktie",$N$5:$N$20,"DEFCON 2*",$O$5:$O$20,"<>🔴*")*'Parameter & Regeln'!$B$27),""))))) -> 95
A8: MSCI World ex-USA | B8: EXUSA | C8: ETF | D8: ING | E8: 0 | F8: 1769.44 | G8: =IF(F$25=0,0,F8/F$25) -> 0.12835553 | H8: 0.15 | I8: =H8*F$25 -> 2067.819 | J8: =I8-F8 -> 298.379 | K8: =G8-H8 -> -0.021644472 | L8: =IF(C8="Aktie",IF(K8>'Parameter & Regeln'!B$9,"📉 Reduzieren",IF(K8<-'Parameter & Regeln'!B$9,"📈 Aufstocken","⚖️ Halten")),IF(K8>'Parameter & Regeln'!B$8,"📉 Reduzieren",IF(K8<-'Parameter & Regeln'!B$8,"📈 Aufstocken","⚖️ Halten"))) -> 📈 Aufstocken | M8: =IF(C8="Aktie",IF(G8>'Parameter & Regeln'!B$10,"🚨 ÜBER CAP","✅ OK"),"") | P8: =IF(OR(C8="ETF",C8="Gold"),(H8/SUMIF($C$5:$C$20,"<>Aktie",$H$5:$H$20))*('Parameter & Regeln'!$B$4*('Parameter & Regeln'!$B$5+'Parameter & Regeln'!$B$7)),IF(C8<>"Aktie","",IF(OR(LEFT(O8,1)="🔴",LEFT(N8,8)="DEFCON 1"),0,IF(LEFT(N8,8)="DEFCON 2",'Parameter & Regeln'!$B$4*'Parameter & Regeln'!$B$6*'Parameter & Regeln'!$B$27/(COUNTIFS($C$5:$C$20,"Aktie",$N$5:$N$20,"DEFCON 4*",$O$5:$O$20,"<>🔴*")+COUNTIFS($C$5:$C$20,"Aktie",$N$5:$N$20,"DEFCON 3*",$O$5:$O$20,"<>🔴*")+COUNTIFS($C$5:$C$20,"Aktie",$N$5:$N$20,"DEFCON 2*",$O$5:$O$20,"<>🔴*")*'Parameter & Regeln'!$B$27),IF(OR(LEFT(N8,8)="DEFCON 4",LEFT(N8,8)="DEFCON 3"),'Parameter & Regeln'!$B$4*'Parameter & Regeln'!$B$6/(COUNTIFS($C$5:$C$20,"Aktie",$N$5:$N$20,"DEFCON 4*",$O$5:$O$20,"<>🔴*")+COUNTIFS($C$5:$C$20,"Aktie",$N$5:$N$20,"DEFCON 3*",$O$5:$O$20,"<>🔴*")+COUNTIFS($C$5:$C$20,"Aktie",$N$5:$N$20,"DEFCON 2*",$O$5:$O$20,"<>🔴*")*'Parameter & Regeln'!$B$27),""))))) -> 142.5
A9: Avantis Small Cap Value | B9: AVGC | C9: ETF | D9: Scalable | E9: 0.67 | F9: 1187 | G9: =IF(F$25=0,0,F9/F$25) -> 0.086105215 | H9: 0.1 | I9: =H9*F$25 -> 1378.546 | J9: =I9-F9 -> 191.546 | K9: =G9-H9 -> -0.013894785 | L9: =IF(C9="Aktie",IF(K9>'Parameter & Regeln'!B$9,"📉 Reduzieren",IF(K9<-'Parameter & Regeln'!B$9,"📈 Aufstocken","⚖️ Halten")),IF(K9>'Parameter & Regeln'!B$8,"📉 Reduzieren",IF(K9<-'Parameter & Regeln'!B$8,"📈 Aufstocken","⚖️ Halten"))) -> ⚖️ Halten | M9: =IF(C9="Aktie",IF(G9>'Parameter & Regeln'!B$10,"🚨 ÜBER CAP","✅ OK"),"") | P9: =IF(OR(C9="ETF",C9="Gold"),(H9/SUMIF($C$5:$C$20,"<>Aktie",$H$5:$H$20))*('Parameter & Regeln'!$B$4*('Parameter & Regeln'!$B$5+'Parameter & Regeln'!$B$7)),IF(C9<>"Aktie","",IF(OR(LEFT(O9,1)="🔴",LEFT(N9,8)="DEFCON 1"),0,IF(LEFT(N9,8)="DEFCON 2",'Parameter & Regeln'!$B$4*'Parameter & Regeln'!$B$6*'Parameter & Regeln'!$B$27/(COUNTIFS($C$5:$C$20,"Aktie",$N$5:$N$20,"DEFCON 4*",$O$5:$O$20,"<>🔴*")+COUNTIFS($C$5:$C$20,"Aktie",$N$5:$N$20,"DEFCON 3*",$O$5:$O$20,"<>🔴*")+COUNTIFS($C$5:$C$20,"Aktie",$N$5:$N$20,"DEFCON 2*",$O$5:$O$20,"<>🔴*")*'Parameter & Regeln'!$B$27),IF(OR(LEFT(N9,8)="DEFCON 4",LEFT(N9,8)="DEFCON 3"),'Parameter & Regeln'!$B$4*'Parameter & Regeln'!$B$6/(COUNTIFS($C$5:$C$20,"Aktie",$N$5:$N$20,"DEFCON 4*",$O$5:$O$20,"<>🔴*")+COUNTIFS($C$5:$C$20,"Aktie",$N$5:$N$20,"DEFCON 3*",$O$5:$O$20,"<>🔴*")+COUNTIFS($C$5:$C$20,"Aktie",$N$5:$N$20,"DEFCON 2*",$O$5:$O$20,"<>🔴*")*'Parameter & Regeln'!$B$27),""))))) -> 95
A10: ASML Holding | B10: ASML | C10: Aktie | D10: Scalable | E10: 0 | F10: 443 | G10: =IF(F$25=0,0,F10/F$25) -> 0.032135308 | H10: 0.0273 | I10: =H10*F$25 -> 376.34306 | J10: =IF(P10=0,0,I10-F10) -> -66.656942 | K10: =G10-H10 -> 0.0048353078 | L10: =IF(C10="Aktie",IF(K10>'Parameter & Regeln'!B$9,"📉 Reduzieren",IF(K10<-'Parameter & Regeln'!B$9,"📈 Aufstocken","⚖️ Halten")),IF(K10>'Parameter & Regeln'!B$8,"📉 Reduzieren",IF(K10<-'Parameter & Regeln'!B$8,"📈 Aufstocken","⚖️ Halten"))) -> ⚖️ Halten | M10: =IF(C10="Aktie",IF(G10>'Parameter & Regeln'!B$10,"🚨 ÜBER CAP","✅ OK"),"") -> ✅ OK | N10: DEFCON 3 (68) | O10: 🟡 DEFCON 3 (68) | China Rev 14.7% Risk-Map | P10: =IF(OR(C10="ETF",C10="Gold"),(H10/SUMIF($C$5:$C$20,"<>Aktie",$H$5:$H$20))*('Parameter & Regeln'!$B$4*('Parameter & Regeln'!$B$5+'Parameter & Regeln'!$B$7)),IF(C10<>"Aktie","",IF(OR(LEFT(O10,1)="🔴",LEFT(N10,8)="DEFCON 1"),0,IF(LEFT(N10,8)="DEFCON 2",'Parameter & Regeln'!$B$4*'Parameter & Regeln'!$B$6*'Parameter & Regeln'!$B$27/(COUNTIFS($C$5:$C$20,"Aktie",$N$5:$N$20,"DEFCON 4*",$O$5:$O$20,"<>🔴*")+COUNTIFS($C$5:$C$20,"Aktie",$N$5:$N$20,"DEFCON 3*",$O$5:$O$20,"<>🔴*")+COUNTIFS($C$5:$C$20,"Aktie",$N$5:$N$20,"DEFCON 2*",$O$5:$O$20,"<>🔴*")*'Parameter & Regeln'!$B$27),IF(OR(LEFT(N10,8)="DEFCON 4",LEFT(N10,8)="DEFCON 3"),'Parameter & Regeln'!$B$4*'Parameter & Regeln'!$B$6/(COUNTIFS($C$5:$C$20,"Aktie",$N$5:$N$20,"DEFCON 4*",$O$5:$O$20,"<>🔴*")+COUNTIFS($C$5:$C$20,"Aktie",$N$5:$N$20,"DEFCON 3*",$O$5:$O$20,"<>🔴*")+COUNTIFS($C$5:$C$20,"Aktie",$N$5:$N$20,"DEFCON 2*",$O$5:$O$20,"<>🔴*")*'Parameter & Regeln'!$B$27),""))))) -> 38
A11: Broadcom | B11: AVGO | C11: Aktie | D11: Scalable | E11: 1 | F11: 516 | G11: =IF(F$25=0,0,F11/F$25) -> 0.037430742 | H11: 0.0273 | I11: =H11*F$25 -> 376.34306 | J11: =IF(P11=0,0,I11-F11) -> 0 | K11: =G11-H11 -> 0.010130742 | L11: =IF(C11="Aktie",IF(K11>'Parameter & Regeln'!B$9,"📉 Reduzieren",IF(K11<-'Parameter & Regeln'!B$9,"📈 Aufstocken","⚖️ Halten")),IF(K11>'Parameter & Regeln'!B$8,"📉 Reduzieren",IF(K11<-'Parameter & Regeln'!B$8,"📈 Aufstocken","⚖️ Halten"))) -> ⚖️ Halten | M11: =IF(C11="Aktie",IF(G11>'Parameter & Regeln'!B$10,"🚨 ÜBER CAP","✅ OK"),"") -> ✅ OK | N11: DEFCON 2 (53) | Vollanalyse 30.04. | O11: 🔴 FLAG: Insider-Selling 90d $106M+ | Aktiviert 27.04.2026 | Vollanalyse 30.04. Score 84→53 (D4→D2) | Re-Eval Q3 FY26 | P11: =IF(OR(C11="ETF",C11="Gold"),(H11/SUMIF($C$5:$C$20,"<>Aktie",$H$5:$H$20))*('Parameter & Regeln'!$B$4*('Parameter & Regeln'!$B$5+'Parameter & Regeln'!$B$7)),IF(C11<>"Aktie","",IF(OR(LEFT(O11,1)="🔴",LEFT(N11,8)="DEFCON 1"),0,IF(LEFT(N11,8)="DEFCON 2",'Parameter & Regeln'!$B$4*'Parameter & Regeln'!$B$6*'Parameter & Regeln'!$B$27/(COUNTIFS($C$5:$C$20,"Aktie",$N$5:$N$20,"DEFCON 4*",$O$5:$O$20,"<>🔴*")+COUNTIFS($C$5:$C$20,"Aktie",$N$5:$N$20,"DEFCON 3*",$O$5:$O$20,"<>🔴*")+COUNTIFS($C$5:$C$20,"Aktie",$N$5:$N$20,"DEFCON 2*",$O$5:$O$20,"<>🔴*")*'Parameter & Regeln'!$B$27),IF(OR(LEFT(N11,8)="DEFCON 4",LEFT(N11,8)="DEFCON 3"),'Parameter & Regeln'!$B$4*'Parameter & Regeln'!$B$6/(COUNTIFS($C$5:$C$20,"Aktie",$N$5:$N$20,"DEFCON 4*",$O$5:$O$20,"<>🔴*")+COUNTIFS($C$5:$C$20,"Aktie",$N$5:$N$20,"DEFCON 3*",$O$5:$O$20,"<>🔴*")+COUNTIFS($C$5:$C$20,"Aktie",$N$5:$N$20,"DEFCON 2*",$O$5:$O$20,"<>🔴*")*'Parameter & Regeln'!$B$27),""))))) -> 0
A12: Microsoft | B12: MSFT | C12: Aktie | D12: Scalable | E12: 1 | F12: 387 | G12: =IF(F$25=0,0,F12/F$25) -> 0.028073057 | H12: 0.0273 | I12: =H12*F$25 -> 376.34306 | J12: =IF(P12=0,0,I12-F12) -> 0 | K12: =G12-H12 -> 0.00077305668 | L12: =IF(C12="Aktie",IF(K12>'Parameter & Regeln'!B$9,"📉 Reduzieren",IF(K12<-'Parameter & Regeln'!B$9,"📈 Aufstocken","⚖️ Halten")),IF(K12>'Parameter & Regeln'!B$8,"📉 Reduzieren",IF(K12<-'Parameter & Regeln'!B$8,"📈 Aufstocken","⚖️ Halten"))) -> ⚖️ Halten | M12: =IF(C12="Aktie",IF(G12>'Parameter & Regeln'!B$10,"🚨 ÜBER CAP","✅ OK"),"") -> ✅ OK | N12: DEFCON 2 (50) | O12: 🔴 FLAG: CapEx/OCF aktiv | Score 50 | DEFCON 2 | Bull-Case Trigger B FAIL (CY26 $190B) | Re-Check Q4 FY26 ~Juli | P12: =IF(OR(C12="ETF",C12="Gold"),(H12/SUMIF($C$5:$C$20,"<>Aktie",$H$5:$H$20))*('Parameter & Regeln'!$B$4*('Parameter & Regeln'!$B$5+'Parameter & Regeln'!$B$7)),IF(C12<>"Aktie","",IF(OR(LEFT(O12,1)="🔴",LEFT(N12,8)="DEFCON 1"),0,IF(LEFT(N12,8)="DEFCON 2",'Parameter & Regeln'!$B$4*'Parameter & Regeln'!$B$6*'Parameter & Regeln'!$B$27/(COUNTIFS($C$5:$C$20,"Aktie",$N$5:$N$20,"DEFCON 4*",$O$5:$O$20,"<>🔴*")+COUNTIFS($C$5:$C$20,"Aktie",$N$5:$N$20,"DEFCON 3*",$O$5:$O$20,"<>🔴*")+COUNTIFS($C$5:$C$20,"Aktie",$N$5:$N$20,"DEFCON 2*",$O$5:$O$20,"<>🔴*")*'Parameter & Regeln'!$B$27),IF(OR(LEFT(N12,8)="DEFCON 4",LEFT(N12,8)="DEFCON 3"),'Parameter & Regeln'!$B$4*'Parameter & Regeln'!$B$6/(COUNTIFS($C$5:$C$20,"Aktie",$N$5:$N$20,"DEFCON 4*",$O$5:$O$20,"<>🔴*")+COUNTIFS($C$5:$C$20,"Aktie",$N$5:$N$20,"DEFCON 3*",$O$5:$O$20,"<>🔴*")+COUNTIFS($C$5:$C$20,"Aktie",$N$5:$N$20,"DEFCON 2*",$O$5:$O$20,"<>🔴*")*'Parameter & Regeln'!$B$27),""))))) -> 0
A13: Costco | B13: COST | C13: Aktie | D13: Scalable | E13: 1 | F13: 404 | G13: =IF(F$25=0,0,F13/F$25) -> 0.02930624 | H13: 0.0273 | I13: =H13*F$25 -> 376.34306 | J13: =IF(P13=0,0,I13-F13) -> -27.656942 | K13: =G13-H13 -> 0.0020062401 | L13: =IF(C13="Aktie",IF(K13>'Parameter & Regeln'!B$9,"📉 Reduzieren",IF(K13<-'Parameter & Regeln'!B$9,"📈 Aufstocken","⚖️ Halten")),IF(K13>'Parameter & Regeln'!B$8,"📉 Reduzieren",IF(K13<-'Parameter & Regeln'!B$8,"📈 Aufstocken","⚖️ Halten"))) -> ⚖️ Halten | M13: =IF(C13="Aktie",IF(G13>'Parameter & Regeln'!B$10,"🚨 ÜBER CAP","✅ OK"),"") -> ✅ OK | N13: DEFCON 3 (69) | MY 15.2% > WACC | O13: ✅ Clean | P13: =IF(OR(C13="ETF",C13="Gold"),(H13/SUMIF($C$5:$C$20,"<>Aktie",$H$5:$H$20))*('Parameter & Regeln'!$B$4*('Parameter & Regeln'!$B$5+'Parameter & Regeln'!$B$7)),IF(C13<>"Aktie","",IF(OR(LEFT(O13,1)="🔴",LEFT(N13,8)="DEFCON 1"),0,IF(LEFT(N13,8)="DEFCON 2",'Parameter & Regeln'!$B$4*'Parameter & Regeln'!$B$6*'Parameter & Regeln'!$B$27/(COUNTIFS($C$5:$C$20,"Aktie",$N$5:$N$20,"DEFCON 4*",$O$5:$O$20,"<>🔴*")+COUNTIFS($C$5:$C$20,"Aktie",$N$5:$N$20,"DEFCON 3*",$O$5:$O$20,"<>🔴*")+COUNTIFS($C$5:$C$20,"Aktie",$N$5:$N$20,"DEFCON 2*",$O$5:$O$20,"<>🔴*")*'Parameter & Regeln'!$B$27),IF(OR(LEFT(N13,8)="DEFCON 4",LEFT(N13,8)="DEFCON 3"),'Parameter & Regeln'!$B$4*'Parameter & Regeln'!$B$6/(COUNTIFS($C$5:$C$20,"Aktie",$N$5:$N$20,"DEFCON 4*",$O$5:$O$20,"<>🔴*")+COUNTIFS($C$5:$C$20,"Aktie",$N$5:$N$20,"DEFCON 3*",$O$5:$O$20,"<>🔴*")+COUNTIFS($C$5:$C$20,"Aktie",$N$5:$N$20,"DEFCON 2*",$O$5:$O$20,"<>🔴*")*'Parameter & Regeln'!$B$27),""))))) -> 38
A14: Hermès | B14: RMS | C14: Aktie | D14: Scalable | E14: 0 | F14: 394 | G14: =IF(F$25=0,0,F14/F$25) -> 0.028580838 | H14: 0.0273 | I14: =H14*F$25 -> 376.34306 | J14: =IF(P14=0,0,I14-F14) -> -17.656942 | K14: =G14-H14 -> 0.0012808381 | L14: =IF(C14="Aktie",IF(K14>'Parameter & Regeln'!B$9,"📉 Reduzieren",IF(K14<-'Parameter & Regeln'!B$9,"📈 Aufstocken","⚖️ Halten")),IF(K14>'Parameter & Regeln'!B$8,"📉 Reduzieren",IF(K14<-'Parameter & Regeln'!B$8,"📈 Aufstocken","⚖️ Halten"))) -> ⚖️ Halten | M14: =IF(C14="Aktie",IF(G14>'Parameter & Regeln'!B$10,"🚨 ÜBER CAP","✅ OK"),"") -> ✅ OK | N14: DEFCON 3 (68) | Q1 Miss: −8.4% | Moat intakt | O14: ✅ Clean | Re-Analyse 17.04.2026 v3.7 | P14: =IF(OR(C14="ETF",C14="Gold"),(H14/SUMIF($C$5:$C$20,"<>Aktie",$H$5:$H$20))*('Parameter & Regeln'!$B$4*('Parameter & Regeln'!$B$5+'Parameter & Regeln'!$B$7)),IF(C14<>"Aktie","",IF(OR(LEFT(O14,1)="🔴",LEFT(N14,8)="DEFCON 1"),0,IF(LEFT(N14,8)="DEFCON 2",'Parameter & Regeln'!$B$4*'Parameter & Regeln'!$B$6*'Parameter & Regeln'!$B$27/(COUNTIFS($C$5:$C$20,"Aktie",$N$5:$N$20,"DEFCON 4*",$O$5:$O$20,"<>🔴*")+COUNTIFS($C$5:$C$20,"Aktie",$N$5:$N$20,"DEFCON 3*",$O$5:$O$20,"<>🔴*")+COUNTIFS($C$5:$C$20,"Aktie",$N$5:$N$20,"DEFCON 2*",$O$5:$O$20,"<>🔴*")*'Parameter & Regeln'!$B$27),IF(OR(LEFT(N14,8)="DEFCON 4",LEFT(N14,8)="DEFCON 3"),'Parameter & Regeln'!$B$4*'Parameter & Regeln'!$B$6/(COUNTIFS($C$5:$C$20,"Aktie",$N$5:$N$20,"DEFCON 4*",$O$5:$O$20,"<>🔴*")+COUNTIFS($C$5:$C$20,"Aktie",$N$5:$N$20,"DEFCON 3*",$O$5:$O$20,"<>🔴*")+COUNTIFS($C$5:$C$20,"Aktie",$N$5:$N$20,"DEFCON 2*",$O$5:$O$20,"<>🔴*")*'Parameter & Regeln'!$B$27),""))))) -> 38
A15: Veeva Systems | B15: VEEV | C15: Aktie | D15: Scalable | E15: 1 | F15: 322 | G15: =IF(F$25=0,0,F15/F$25) -> 0.023357944 | H15: 0.0273 | I15: =H15*F$25 -> 376.34306 | J15: =IF(P15=0,0,I15-F15) -> 54.343058 | K15: =G15-H15 -> -0.0039420562 | L15: =IF(C15="Aktie",IF(K15>'Parameter & Regeln'!B$9,"📉 Reduzieren",IF(K15<-'Parameter & Regeln'!B$9,"📈 Aufstocken","⚖️ Halten")),IF(K15>'Parameter & Regeln'!B$8,"📉 Reduzieren",IF(K15<-'Parameter & Regeln'!B$8,"📈 Aufstocken","⚖️ Halten"))) -> ⚖️ Halten | M15: =IF(C15="Aktie",IF(G15>'Parameter & Regeln'!B$10,"🚨 ÜBER CAP","✅ OK"),"") -> ✅ OK | N15: DEFCON 3 (74) | O15: ✅ Clean | P15: =IF(OR(C15="ETF",C15="Gold"),(H15/SUMIF($C$5:$C$20,"<>Aktie",$H$5:$H$20))*('Parameter & Regeln'!$B$4*('Parameter & Regeln'!$B$5+'Parameter & Regeln'!$B$7)),IF(C15<>"Aktie","",IF(OR(LEFT(O15,1)="🔴",LEFT(N15,8)="DEFCON 1"),0,IF(LEFT(N15,8)="DEFCON 2",'Parameter & Regeln'!$B$4*'Parameter & Regeln'!$B$6*'Parameter & Regeln'!$B$27/(COUNTIFS($C$5:$C$20,"Aktie",$N$5:$N$20,"DEFCON 4*",$O$5:$O$20,"<>🔴*")+COUNTIFS($C$5:$C$20,"Aktie",$N$5:$N$20,"DEFCON 3*",$O$5:$O$20,"<>🔴*")+COUNTIFS($C$5:$C$20,"Aktie",$N$5:$N$20,"DEFCON 2*",$O$5:$O$20,"<>🔴*")*'Parameter & Regeln'!$B$27),IF(OR(LEFT(N15,8)="DEFCON 4",LEFT(N15,8)="DEFCON 3"),'Parameter & Regeln'!$B$4*'Parameter & Regeln'!$B$6/(COUNTIFS($C$5:$C$20,"Aktie",$N$5:$N$20,"DEFCON 4*",$O$5:$O$20,"<>🔴*")+COUNTIFS($C$5:$C$20,"Aktie",$N$5:$N$20,"DEFCON 3*",$O$5:$O$20,"<>🔴*")+COUNTIFS($C$5:$C$20,"Aktie",$N$5:$N$20,"DEFCON 2*",$O$5:$O$20,"<>🔴*")*'Parameter & Regeln'!$B$27),""))))) -> 38
A16: Schneider Electric | B16: SU | C16: Aktie | D16: Scalable | E16: 0 | F16: 407 | G16: =IF(F$25=0,0,F16/F$25) -> 0.029523861 | H16: 0.0273 | I16: =H16*F$25 -> 376.34306 | J16: =IF(P16=0,0,I16-F16) -> -30.656942 | K16: =G16-H16 -> 0.0022238606 | L16: =IF(C16="Aktie",IF(K16>'Parameter & Regeln'!B$9,"📉 Reduzieren",IF(K16<-'Parameter & Regeln'!B$9,"📈 Aufstocken","⚖️ Halten")),IF(K16>'Parameter & Regeln'!B$8,"📉 Reduzieren",IF(K16<-'Parameter & Regeln'!B$8,"📈 Aufstocken","⚖️ Halten"))) -> ⚖️ Halten | M16: =IF(C16="Aktie",IF(G16>'Parameter & Regeln'!B$10,"🚨 ÜBER CAP","✅ OK"),"") -> ✅ OK | N16: DEFCON 3 (69) | O16: ✅ Clean | P16: =IF(OR(C16="ETF",C16="Gold"),(H16/SUMIF($C$5:$C$20,"<>Aktie",$H$5:$H$20))*('Parameter & Regeln'!$B$4*('Parameter & Regeln'!$B$5+'Parameter & Regeln'!$B$7)),IF(C16<>"Aktie","",IF(OR(LEFT(O16,1)="🔴",LEFT(N16,8)="DEFCON 1"),0,IF(LEFT(N16,8)="DEFCON 2",'Parameter & Regeln'!$B$4*'Parameter & Regeln'!$B$6*'Parameter & Regeln'!$B$27/(COUNTIFS($C$5:$C$20,"Aktie",$N$5:$N$20,"DEFCON 4*",$O$5:$O$20,"<>🔴*")+COUNTIFS($C$5:$C$20,"Aktie",$N$5:$N$20,"DEFCON 3*",$O$5:$O$20,"<>🔴*")+COUNTIFS($C$5:$C$20,"Aktie",$N$5:$N$20,"DEFCON 2*",$O$5:$O$20,"<>🔴*")*'Parameter & Regeln'!$B$27),IF(OR(LEFT(N16,8)="DEFCON 4",LEFT(N16,8)="DEFCON 3"),'Parameter & Regeln'!$B$4*'Parameter & Regeln'!$B$6/(COUNTIFS($C$5:$C$20,"Aktie",$N$5:$N$20,"DEFCON 4*",$O$5:$O$20,"<>🔴*")+COUNTIFS($C$5:$C$20,"Aktie",$N$5:$N$20,"DEFCON 3*",$O$5:$O$20,"<>🔴*")+COUNTIFS($C$5:$C$20,"Aktie",$N$5:$N$20,"DEFCON 2*",$O$5:$O$20,"<>🔴*")*'Parameter & Regeln'!$B$27),""))))) -> 38
A17: Berkshire Hathaway | B17: BRK.B | C17: Aktie | D17: Scalable | E17: 1 | F17: 440 | G17: =IF(F$25=0,0,F17/F$25) -> 0.031917687 | H17: 0.0273 | I17: =H17*F$25 -> 376.34306 | J17: =IF(P17=0,0,I17-F17) -> -63.656942 | K17: =G17-H17 -> 0.0046176872 | L17: =IF(C17="Aktie",IF(K17>'Parameter & Regeln'!B$9,"📉 Reduzieren",IF(K17<-'Parameter & Regeln'!B$9,"📈 Aufstocken","⚖️ Halten")),IF(K17>'Parameter & Regeln'!B$8,"📉 Reduzieren",IF(K17<-'Parameter & Regeln'!B$8,"📈 Aufstocken","⚖️ Halten"))) -> ⚖️ Halten | M17: =IF(C17="Aktie",IF(G17>'Parameter & Regeln'!B$10,"🚨 ÜBER CAP","✅ OK"),"") -> ✅ OK | N17: DEFCON 3 (71) | Abel Käufe $15.3M | O17: ✅ Clean | P17: =IF(OR(C17="ETF",C17="Gold"),(H17/SUMIF($C$5:$C$20,"<>Aktie",$H$5:$H$20))*('Parameter & Regeln'!$B$4*('Parameter & Regeln'!$B$5+'Parameter & Regeln'!$B$7)),IF(C17<>"Aktie","",IF(OR(LEFT(O17,1)="🔴",LEFT(N17,8)="DEFCON 1"),0,IF(LEFT(N17,8)="DEFCON 2",'Parameter & Regeln'!$B$4*'Parameter & Regeln'!$B$6*'Parameter & Regeln'!$B$27/(COUNTIFS($C$5:$C$20,"Aktie",$N$5:$N$20,"DEFCON 4*",$O$5:$O$20,"<>🔴*")+COUNTIFS($C$5:$C$20,"Aktie",$N$5:$N$20,"DEFCON 3*",$O$5:$O$20,"<>🔴*")+COUNTIFS($C$5:$C$20,"Aktie",$N$5:$N$20,"DEFCON 2*",$O$5:$O$20,"<>🔴*")*'Parameter & Regeln'!$B$27),IF(OR(LEFT(N17,8)="DEFCON 4",LEFT(N17,8)="DEFCON 3"),'Parameter & Regeln'!$B$4*'Parameter & Regeln'!$B$6/(COUNTIFS($C$5:$C$20,"Aktie",$N$5:$N$20,"DEFCON 4*",$O$5:$O$20,"<>🔴*")+COUNTIFS($C$5:$C$20,"Aktie",$N$5:$N$20,"DEFCON 3*",$O$5:$O$20,"<>🔴*")+COUNTIFS($C$5:$C$20,"Aktie",$N$5:$N$20,"DEFCON 2*",$O$5:$O$20,"<>🔴*")*'Parameter & Regeln'!$B$27),""))))) -> 38
A18: Visa | B18: V | C18: Aktie | D18: Scalable | E18: 1 | F18: 478 | G18: =IF(F$25=0,0,F18/F$25) -> 0.034674215 | H18: 0.0273 | I18: =H18*F$25 -> 376.34306 | J18: =IF(P18=0,0,I18-F18) -> -101.65694 | K18: =G18-H18 -> 0.0073742147 | L18: =IF(C18="Aktie",IF(K18>'Parameter & Regeln'!B$9,"📉 Reduzieren",IF(K18<-'Parameter & Regeln'!B$9,"📈 Aufstocken","⚖️ Halten")),IF(K18>'Parameter & Regeln'!B$8,"📉 Reduzieren",IF(K18<-'Parameter & Regeln'!B$8,"📈 Aufstocken","⚖️ Halten"))) -> ⚖️ Halten | M18: =IF(C18="Aktie",IF(G18>'Parameter & Regeln'!B$10,"🚨 ÜBER CAP","✅ OK"),"") -> ✅ OK | N18: DEFCON 2 (64) | O18: 🟠 DEFCON 2 (64) | Q2 Beat-Cascade D3 (mittags) → Codex-Review-Revert D2 (spätabends, HIGH-1+2 28.04.) | Q3 ~Ende Juli ROIC-Verify | P18: =IF(OR(C18="ETF",C18="Gold"),(H18/SUMIF($C$5:$C$20,"<>Aktie",$H$5:$H$20))*('Parameter & Regeln'!$B$4*('Parameter & Regeln'!$B$5+'Parameter & Regeln'!$B$7)),IF(C18<>"Aktie","",IF(OR(LEFT(O18,1)="🔴",LEFT(N18,8)="DEFCON 1"),0,IF(LEFT(N18,8)="DEFCON 2",'Parameter & Regeln'!$B$4*'Parameter & Regeln'!$B$6*'Parameter & Regeln'!$B$27/(COUNTIFS($C$5:$C$20,"Aktie",$N$5:$N$20,"DEFCON 4*",$O$5:$O$20,"<>🔴*")+COUNTIFS($C$5:$C$20,"Aktie",$N$5:$N$20,"DEFCON 3*",$O$5:$O$20,"<>🔴*")+COUNTIFS($C$5:$C$20,"Aktie",$N$5:$N$20,"DEFCON 2*",$O$5:$O$20,"<>🔴*")*'Parameter & Regeln'!$B$27),IF(OR(LEFT(N18,8)="DEFCON 4",LEFT(N18,8)="DEFCON 3"),'Parameter & Regeln'!$B$4*'Parameter & Regeln'!$B$6/(COUNTIFS($C$5:$C$20,"Aktie",$N$5:$N$20,"DEFCON 4*",$O$5:$O$20,"<>🔴*")+COUNTIFS($C$5:$C$20,"Aktie",$N$5:$N$20,"DEFCON 3*",$O$5:$O$20,"<>🔴*")+COUNTIFS($C$5:$C$20,"Aktie",$N$5:$N$20,"DEFCON 2*",$O$5:$O$20,"<>🔴*")*'Parameter & Regeln'!$B$27),""))))) -> 19
A19: Thermo Fisher | B19: TMO | C19: Aktie | D19: Scalable | E19: 1 | F19: 305 | G19: =IF(F$25=0,0,F19/F$25) -> 0.02212476 | H19: 0.0273 | I19: =H19*F$25 -> 376.34306 | J19: =IF(P19=0,0,I19-F19) -> 71.343058 | K19: =G19-H19 -> -0.0051752396 | L19: =IF(C19="Aktie",IF(K19>'Parameter & Regeln'!B$9,"📉 Reduzieren",IF(K19<-'Parameter & Regeln'!B$9,"📈 Aufstocken","⚖️ Halten")),IF(K19>'Parameter & Regeln'!B$8,"📉 Reduzieren",IF(K19<-'Parameter & Regeln'!B$8,"📈 Aufstocken","⚖️ Halten"))) -> ⚖️ Halten | M19: =IF(C19="Aktie",IF(G19>'Parameter & Regeln'!B$10,"🚨 ÜBER CAP","✅ OK"),"") -> ✅ OK | N19: DEFCON 3 (67) | O19: 🟡 DEFCON 3 (67) | fcf_trend_neg Resolve (Q1 WC-Unwind bestätigt) | Q2 ~Ende Juli | P19: =IF(OR(C19="ETF",C19="Gold"),(H19/SUMIF($C$5:$C$20,"<>Aktie",$H$5:$H$20))*('Parameter & Regeln'!$B$4*('Parameter & Regeln'!$B$5+'Parameter & Regeln'!$B$7)),IF(C19<>"Aktie","",IF(OR(LEFT(O19,1)="🔴",LEFT(N19,8)="DEFCON 1"),0,IF(LEFT(N19,8)="DEFCON 2",'Parameter & Regeln'!$B$4*'Parameter & Regeln'!$B$6*'Parameter & Regeln'!$B$27/(COUNTIFS($C$5:$C$20,"Aktie",$N$5:$N$20,"DEFCON 4*",$O$5:$O$20,"<>🔴*")+COUNTIFS($C$5:$C$20,"Aktie",$N$5:$N$20,"DEFCON 3*",$O$5:$O$20,"<>🔴*")+COUNTIFS($C$5:$C$20,"Aktie",$N$5:$N$20,"DEFCON 2*",$O$5:$O$20,"<>🔴*")*'Parameter & Regeln'!$B$27),IF(OR(LEFT(N19,8)="DEFCON 4",LEFT(N19,8)="DEFCON 3"),'Parameter & Regeln'!$B$4*'Parameter & Regeln'!$B$6/(COUNTIFS($C$5:$C$20,"Aktie",$N$5:$N$20,"DEFCON 4*",$O$5:$O$20,"<>🔴*")+COUNTIFS($C$5:$C$20,"Aktie",$N$5:$N$20,"DEFCON 3*",$O$5:$O$20,"<>🔴*")+COUNTIFS($C$5:$C$20,"Aktie",$N$5:$N$20,"DEFCON 2*",$O$5:$O$20,"<>🔴*")*'Parameter & Regeln'!$B$27),""))))) -> 38
A20: Amphenol | B20: APH | C20: Aktie | D20: Scalable | E20: 1 | F20: 297 | G20: =IF(F$25=0,0,F20/F$25) -> 0.021544439 | H20: 0.027 | I20: =H20*F$25 -> 372.20742 | J20: =IF(P20=0,0,I20-F20) -> 0 | K20: =G20-H20 -> -0.0054555611 | L20: =IF(C20="Aktie",IF(K20>'Parameter & Regeln'!B$9,"📉 Reduzieren",IF(K20<-'Parameter & Regeln'!B$9,"📈 Aufstocken","⚖️ Halten")),IF(K20>'Parameter & Regeln'!B$8,"📉 Reduzieren",IF(K20<-'Parameter & Regeln'!B$8,"📈 Aufstocken","⚖️ Halten"))) -> ⚖️ Halten | M20: =IF(C20="Aktie",IF(G20>'Parameter & Regeln'!B$10,"🚨 ÜBER CAP","✅ OK"),"") -> ✅ OK | N20: DEFCON 2 (61) | O20: 🔴 FLAG: Score 61 (DEFCON 2, Q1 FY26 Tag-+1 Vollanalyse 30.04.) | CommScope-NL 1,6x | China-Tax-ETR 27% strukturell | P20: =IF(OR(C20="ETF",C20="Gold"),(H20/SUMIF($C$5:$C$20,"<>Aktie",$H$5:$H$20))*('Parameter & Regeln'!$B$4*('Parameter & Regeln'!$B$5+'Parameter & Regeln'!$B$7)),IF(C20<>"Aktie","",IF(OR(LEFT(O20,1)="🔴",LEFT(N20,8)="DEFCON 1"),0,IF(LEFT(N20,8)="DEFCON 2",'Parameter & Regeln'!$B$4*'Parameter & Regeln'!$B$6*'Parameter & Regeln'!$B$27/(COUNTIFS($C$5:$C$20,"Aktie",$N$5:$N$20,"DEFCON 4*",$O$5:$O$20,"<>🔴*")+COUNTIFS($C$5:$C$20,"Aktie",$N$5:$N$20,"DEFCON 3*",$O$5:$O$20,"<>🔴*")+COUNTIFS($C$5:$C$20,"Aktie",$N$5:$N$20,"DEFCON 2*",$O$5:$O$20,"<>🔴*")*'Parameter & Regeln'!$B$27),IF(OR(LEFT(N20,8)="DEFCON 4",LEFT(N20,8)="DEFCON 3"),'Parameter & Regeln'!$B$4*'Parameter & Regeln'!$B$6/(COUNTIFS($C$5:$C$20,"Aktie",$N$5:$N$20,"DEFCON 4*",$O$5:$O$20,"<>🔴*")+COUNTIFS($C$5:$C$20,"Aktie",$N$5:$N$20,"DEFCON 3*",$O$5:$O$20,"<>🔴*")+COUNTIFS($C$5:$C$20,"Aktie",$N$5:$N$20,"DEFCON 2*",$O$5:$O$20,"<>🔴*")*'Parameter & Regeln'!$B$27),""))))) -> 0
A21: 📊 GESAMT | F21: =SUM(F5:F20) -> 12835.46 | G21: =SUM(G5:G20) -> 0.93108681 | H21: =SUM(H5:H20) -> 1 | I21: =SUM(I5:I20) -> 13785.46 | J21: =ROUND(SUM(J5:J20),2) -> 1025.11 | K21: =SUMPRODUCT((C5:C20="Aktie")*ABS(K5:K20))/COUNTIF(C5:C20,"Aktie") -> 0.0043468004 | L21: Ø Drift ges. | M21: =COUNTIF(M5:M20,"🚨 ÜBER CAP") -> 0 | N21: =COUNTIF(N5:N20,"DEFCON 1*")+COUNTIF(N5:N20,"DEFCON 2*")+COUNTIF(N5:N20,"DEFCON 3*") -> 11 | O21: =COUNTIF(O5:O20,"🚩*")+COUNTIF(O5:O20,"🔴*") -> 3 | P21: =SUMIF(C5:C20,"Aktie",P5:P20)+SUMIF(C5:C20,"<>Aktie",P5:P20) -> 950
K22: =SUMPRODUCT((C5:C20<>"Aktie")*ABS(K5:K20))/COUNTIF(C5:C20,"<>Aktie") -> 0.017516456 | L22: Ø ETF/Gold-Drift | M22: =COUNTIF(M5:M9,"🚨 ÜBER CAP") -> 0 | N22: ⚠️ DEFCON ≤ 3 | O22: 🚩 Aktive FLAGs | P22: Check: Sparrate gesamt
A23: Scalable Cash (verfügbar) | F23: 1297.78
A24: 📝 Neuinvestition (manuell eingeben) | F24: 950
A25: Gesamtwert nach Invest | F25: =F21 + F24 -> 13785.46
A26: Noch zu überweisen (ING + Δ Scalable) | F26: =F24 - MIN(F23, SUMIFS(J5:J20, D5:D20, "Scalable", J5:J20, ">0")) -> 525.49488

Sheet US-Exposure
A1: US-EXPOSURE TRACKER
A3: Position | B3: Ticker | C3: Depotwert € | D3: US-Faktor | E3: US-Anteil €
A4: ='Portfolio & Rebalancing'!A5 -> EUWAX Gold | B4: ='Portfolio & Rebalancing'!B5 -> EWG2 | C4: ='Portfolio & Rebalancing'!F5 -> 582 | D4: ='Portfolio & Rebalancing'!E5 -> 0 | E4: =C4*D4 -> 0
A5: ='Portfolio & Rebalancing'!A6 -> iShares MSCI World | B5: ='Portfolio & Rebalancing'!B6 -> IWDA | C5: ='Portfolio & Rebalancing'!F6 -> 3675.72 | D5: ='Portfolio & Rebalancing'!E6 -> 0.7 | E5: =C5*D5 -> 2573.004
A6: ='Portfolio & Rebalancing'!A7 -> iShares MSCI EM IMI | B6: ='Portfolio & Rebalancing'!B7 -> EIMI | C6: ='Portfolio & Rebalancing'!F7 -> 1228.3 | D6: ='Portfolio & Rebalancing'!E7 -> 0 | E6: =C6*D6 -> 0
A7: ='Portfolio & Rebalancing'!A8 -> MSCI World ex-USA | B7: ='Portfolio & Rebalancing'!B8 -> EXUSA | C7: ='Portfolio & Rebalancing'!F8 -> 1769.44 | D7: ='Portfolio & Rebalancing'!E8 -> 0 | E7: =C7*D7 -> 0
A8: ='Portfolio & Rebalancing'!A9 -> Avantis Small Cap Value | B8: ='Portfolio & Rebalancing'!B9 -> AVGC | C8: ='Portfolio & Rebalancing'!F9 -> 1187 | D8: ='Portfolio & Rebalancing'!E9 -> 0.67 | E8: =C8*D8 -> 795.29
A9: ='Portfolio & Rebalancing'!A10 -> ASML Holding | B9: ='Portfolio & Rebalancing'!B10 -> ASML | C9: ='Portfolio & Rebalancing'!F10 -> 443 | D9: ='Portfolio & Rebalancing'!E10 -> 0 | E9: =C9*D9 -> 0
A10: ='Portfolio & Rebalancing'!A11 -> Broadcom | B10: ='Portfolio & Rebalancing'!B11 -> AVGO | C10: ='Portfolio & Rebalancing'!F11 -> 516 | D10: ='Portfolio & Rebalancing'!E11 -> 1 | E10: =C10*D10 -> 516
A11: ='Portfolio & Rebalancing'!A12 -> Microsoft | B11: ='Portfolio & Rebalancing'!B12 -> MSFT | C11: ='Portfolio & Rebalancing'!F12 -> 387 | D11: ='Portfolio & Rebalancing'!E12 -> 1 | E11: =C11*D11 -> 387
A12: ='Portfolio & Rebalancing'!A13 -> Costco | B12: ='Portfolio & Rebalancing'!B13 -> COST | C12: ='Portfolio & Rebalancing'!F13 -> 404 | D12: ='Portfolio & Rebalancing'!E13 -> 1 | E12: =C12*D12 -> 404
A13: ='Portfolio & Rebalancing'!A14 -> Hermès | B13: ='Portfolio & Rebalancing'!B14 -> RMS | C13: ='Portfolio & Rebalancing'!F14 -> 394 | D13: ='Portfolio & Rebalancing'!E14 -> 0 | E13: =C13*D13 -> 0
A14: ='Portfolio & Rebalancing'!A15 -> Veeva Systems | B14: ='Portfolio & Rebalancing'!B15 -> VEEV | C14: ='Portfolio & Rebalancing'!F15 -> 322 | D14: ='Portfolio & Rebalancing'!E15 -> 1 | E14: =C14*D14 -> 322
A15: ='Portfolio & Rebalancing'!A16 -> Schneider Electric | B15: ='Portfolio & Rebalancing'!B16 -> SU | C15: ='Portfolio & Rebalancing'!F16 -> 407 | D15: ='Portfolio & Rebalancing'!E16 -> 0 | E15: =C15*D15 -> 0
... A19: ='Portfolio & Rebalancing'!A20 -> Amphenol | B19: ='Portfolio & Rebalancing'!B20 -> APH | C19: ='Portfolio & Rebalancing'!F20 -> 297 | D19: ='Portfolio & Rebalancing'!E20 -> 1 | E19: =C19*D19 -> 297
A20: GESAMT | C20: ='Portfolio & Rebalancing'!F21 -> 12835.46 | E20: =SUM(E4:E19) -> 6517.294
A22: US-Anteil (Ist) | B22: =IF('Portfolio & Rebalancing'!F25=0,0,E20/'Portfolio & Rebalancing'!F25) -> 0.4727658
A23: US-Anteil (Ziel) | B23: =SUMPRODUCT('Portfolio & Rebalancing'!$E$5:$E$20,'Portfolio & Rebalancing'!$I$5:$I$20)/SUM('Portfolio & Rebalancing'!$I$5:$I$20) -> 0.4951
A24: US-Hard-Cap | B24: ='Parameter & Regeln'!B11 -> 0.63
A25: Status (Ist) | B25: =IF(B22>B24,"⛔ ÜBER CAP","✅ OK") -> ✅ OK
A26: Status (Ziel) | B26: =IF(B23>B24,"⛔ ZIEL ÜBER CAP","✅ Ziel OK") -> ✅ Ziel OK

Sheet Parameter & Regeln
A1: ⚙️ REBALANCING PARAMETER
A3: Parameter | B3: Wert | C3: Einheit
A4: Sparrate monatlich | B4: 950 | C4: €
A5: ETF-Core Zielanteil | B5: 0.65 | C5: %
A6: Satelliten Zielanteil | B6: 0.3 | C6: %
A7: Gold Zielanteil | B7: 0.05 | C7: %
A8: Drift-Toleranz ETF/Gold | B8: 0.015 | C8: %
A9: Drift-Toleranz Aktien | B9: 0.04 | C9: %
A10: Single-Stock-Cap | B10: 0.1 | C10: %
A11: US-Hard-Cap | B11: 0.63 | C11: %
A12: Max Aktien Slots | B12: 11
A13: Aktien-Slots belegt | B13: =COUNTIF('Portfolio & Rebalancing'!C5:C20,"Aktie") -> 11
A14: Gesamt Positionen belegt | B14: =COUNTA('Portfolio & Rebalancing'!A5:A20) -> 16
A15: Drift-Warnschwelle (Faktor × Toleranz → K rot) | B15: 3 | C15: ×
A16: Allokations-Check (Summe ETF+Sat+Gold) | B16: =B5+B6+B7 -> 1 | C16: %
A17: 📋 REBALANCING-REGELN
A19: Situation | B19: Bedeutung | C19: Aktion
A20: Abweichung negativ (rot) | B20: Untergewicht | C20: 📈 Sparrate erhöhen/starten
A21: Abweichung positiv (gelb) | B21: Übergewicht | C21: 📉 Sparrate stoppen/drosseln
A22: Innerhalb Toleranz (grün) | B22: Gleichgewicht | C22: ⚖️ Sparrate weiterführen
A23: NIEMALS durch Verkauf rebalancen | B23: Steuer-Bremse | C23: Nur Sparplan umleiten
A25: Satelliten-Budget / Monat | B25: =B4*B6 -> 285 | C25: €
A26: Aktive Aktien-Sparrate (D4/D3, kein 🔴 FLAG) | B26: =COUNTIFS('Portfolio & Rebalancing'!C5:C20,"Aktie",'Portfolio & Rebalancing'!N5:N20,"DEFCON 4*",'Portfolio & Rebalancing'!O5:O20,"<>🔴*")+COUNTIFS('Portfolio & Rebalancing'!C5:C20,"Aktie",'Portfolio & Rebalancing'!N5:N20,"DEFCON 3*",'Portfolio & Rebalancing'!O5:O20,"<>🔴*") -> 7
A27: DEFCON-2-Sockelbetrag (% der vollen Rate) | B27: 0.5 | C27: %
A28: 📋 DEFCON-SPARRATEN-LOGIK
A29: DEFCON 4 oder 3 (kein 🔴 FLAG) | B29: Volle Sparrate (Gewicht 1.0) | C29: Budget ÷ Σ Gewichte × 1.0
A30: DEFCON 2 (kein 🔴 FLAG) | B30: 50% Sockelbetrag (Gewicht 0.5) | C30: Budget ÷ Σ Gewichte × 0.5 — Position halten
A31: DEFCON 1 (egal welcher FLAG) | B31: 0 € – eingefroren | C31: Exit-Kandidat — Auswechslung prüfen
A32: 🔴 FLAG (egal welcher DEFCON) | B32: 0 € – eingefroren | C32: 🔴 FLAG überschreibt jeden Score
